FastAPIDoc/__init__.py
FastAPIDoc/main.py
FastAPIDoc/toSwagger2.py
FastAPIDoc/static/json/group.json
FastAPIDoc/static/json/server1.json
FastAPIDoc/static/swagger2Vue/doc.html
FastAPIDoc/static/swagger2Vue/favicon.ico
FastAPIDoc/static/swagger2Vue/robots.txt
FastAPIDoc/static/swagger2Vue/webjars/css/app.3167b4c3.css
FastAPIDoc/static/swagger2Vue/webjars/fonts/fontawesome-webfont.706450d7.ttf
FastAPIDoc/static/swagger2Vue/webjars/fonts/fontawesome-webfont.97493d3f.woff2
FastAPIDoc/static/swagger2Vue/webjars/fonts/fontawesome-webfont.d9ee23d5.woff
FastAPIDoc/static/swagger2Vue/webjars/fonts/fontawesome-webfont.f7c2b4b7.eot
FastAPIDoc/static/swagger2Vue/webjars/fonts/iconfont.4ca3d0c0.ttf
FastAPIDoc/static/swagger2Vue/webjars/fonts/iconfont.e2d2b98e.eot
FastAPIDoc/static/swagger2Vue/webjars/img/editormd-logo.84b6c2a9.svg
FastAPIDoc/static/swagger2Vue/webjars/img/fontawesome-webfont.139e74e2.svg
FastAPIDoc/static/swagger2Vue/webjars/img/iconfont.1d48c203.svg
FastAPIDoc/static/swagger2Vue/webjars/img/loading.c929501e.gif
FastAPIDoc/static/swagger2Vue/webjars/img/loading@2x.695405a9.gif
FastAPIDoc/static/swagger2Vue/webjars/img/loading@3x.65eacf61.gif
FastAPIDoc/static/swagger2Vue/webjars/img/logo.d03f7d43.png
FastAPIDoc/static/swagger2Vue/webjars/js/app.9f299301.js
FastAPIDoc/static/swagger2Vue/webjars/js/chunk-vendors.07e8b475.js
FastAPIDoc/test/t1.py
FastAPIDoc-0.1.1.dist-info/LICENSE
FastAPIDoc-0.1.1.dist-info/METADATA
FastAPIDoc-0.1.1.dist-info/WHEEL
FastAPIDoc-0.1.1.dist-info/top_level.txt
FastAPIDoc-0.1.1.dist-info/RECORD
