Metadata-Version: 2.1
Name: FastAPIDoc
Version: 0.1.1
Summary: FastAPI Better documentation
Home-page: https://github.com/lsm1103
Author: XiaoMin
Author-email: 18370872400@163.com
License: UNKNOWN
Platform: UNKNOWN
Requires-Dist: fastapi (>=0.61)
Requires-Dist: aiofiles
Requires-Dist: uvicorn
